bb/__init__.py
BB_Chen_Weilin-0.0.2.dist-info/METADATA
BB_Chen_Weilin-0.0.2.dist-info/WHEEL
BB_Chen_Weilin-0.0.2.dist-info/top_level.txt
BB_Chen_Weilin-0.0.2.dist-info/RECORD
