Metadata-Version: 2.1
Name: BB-Chen-Weilin
Version: 0.0.2
Summary: write for bb
Home-page: https://github.com/ChenWeilinx/Fun_old_b
Author: Chen Weilin
Author-email: 2735378542@qq.com
License: MIT
Requires-Python: >=3.8
